COPYING
ChangeLog
MANIFEST.in
epydoc.conf
setup.py
cloudfiles/__init__.py
cloudfiles/authentication.py
cloudfiles/connection.py
cloudfiles/consts.py
cloudfiles/container.py
cloudfiles/errors.py
cloudfiles/fjson.py
cloudfiles/storage_object.py
cloudfiles/utils.py
docs/api-objects.txt
docs/class-tree.html
docs/cloudfiles-module.html
docs/cloudfiles-pysrc.html
docs/cloudfiles.connection-module.html
docs/cloudfiles.connection-pysrc.html
docs/cloudfiles.connection.Connection-class.html
docs/cloudfiles.connection.ConnectionPool-class.html
docs/cloudfiles.container-module.html
docs/cloudfiles.container-pysrc.html
docs/cloudfiles.container.Container-class.html
docs/cloudfiles.container.ContainerResults-class.html
docs/cloudfiles.errors-module.html
docs/cloudfiles.errors-pysrc.html
docs/cloudfiles.errors.AuthenticationError-class.html
docs/cloudfiles.errors.AuthenticationFailed-class.html
docs/cloudfiles.errors.CDNNotEnabled-class.html
docs/cloudfiles.errors.ContainerNotEmpty-class.html
docs/cloudfiles.errors.ContainerNotPublic-class.html
docs/cloudfiles.errors.IncompleteSend-class.html
docs/cloudfiles.errors.InvalidContainerName-class.html
docs/cloudfiles.errors.InvalidMetaName-class.html
docs/cloudfiles.errors.InvalidMetaValue-class.html
docs/cloudfiles.errors.InvalidObjectName-class.html
docs/cloudfiles.errors.InvalidObjectSize-class.html
docs/cloudfiles.errors.InvalidUrl-class.html
docs/cloudfiles.errors.NoSuchContainer-class.html
docs/cloudfiles.errors.NoSuchObject-class.html
docs/cloudfiles.errors.ResponseError-class.html
docs/cloudfiles.fjson-module.html
docs/cloudfiles.fjson-pysrc.html
docs/cloudfiles.storage_object-module.html
docs/cloudfiles.storage_object-pysrc.html
docs/cloudfiles.storage_object.Object-class.html
docs/cloudfiles.storage_object.ObjectResults-class.html
docs/crarr.png
docs/epydoc.css
docs/epydoc.js
docs/frames.html
docs/help.html
docs/identifier-index.html
docs/index.html
docs/module-tree.html
docs/redirect.html
docs/toc-cloudfiles-module.html
python_cloudfiles.egg-info/PKG-INFO
python_cloudfiles.egg-info/SOURCES.txt
python_cloudfiles.egg-info/dependency_links.txt
python_cloudfiles.egg-info/namespace_packages.txt
python_cloudfiles.egg-info/not-zip-safe
python_cloudfiles.egg-info/top_level.txt
